datetransform/__init__.py
datetransform/transform.py
datetransform-0.2.0.dist-info/LICENSE
datetransform-0.2.0.dist-info/METADATA
datetransform-0.2.0.dist-info/WHEEL
datetransform-0.2.0.dist-info/top_level.txt
datetransform-0.2.0.dist-info/RECORD
